autodirwatchdog/__init__.py
autodirwatchdog/core.py
autodirwatchdog-0.1.0.dist-info/METADATA
autodirwatchdog-0.1.0.dist-info/WHEEL
autodirwatchdog-0.1.0.dist-info/top_level.txt
autodirwatchdog-0.1.0.dist-info/RECORD
