Metadata-Version: 2.4
Name: autodirwatchdog
Version: 0.1.0
Summary: Automatically watch a folder and process files (rename and move).
Author: Venky
Author-email: your_email@example.com
Classifier: Programming Language :: Python :: 3
Classifier: License :: OSI Approved :: MIT License
Classifier: Operating System :: OS Independent
Requires-Python: >=3.6
Dynamic: author
Dynamic: author-email
Dynamic: classifier
Dynamic: requires-python
Dynamic: summary
